lab5/counter.v
module counter #(parameter size=8, parameter init={size{1'b1}})(input clk, input rst_b, input c_up, input clr, output reg [size-1 : 0] q);
  
  always @(posedge clk, rst_b) begin
    if(!rst_b)q<=init;
    else begin
      if(clr)q<=init;
      else if(c_up)q<=q+1;
    end
    if(q=={size{1'b1}})q<=0;
  end
endmodule

module counter_tb;
  parameter size=8;
  parameter init={size{1'b1}};
  reg clk,rst_b,c_up,clr;
  wire [size-1 : 0] q;
  
  counter #(
    .size(size),
    .init(init)
    ) dut (
    .clk(clk),
    .rst_b(rst_b),
    .c_up(c_up),
    .clr(clr),
    .q(q)
    );
    
    
    
    initial begin
      clk=0;
      //#5;
      repeat(100) #5 clk=~clk;
    end
    
    initial begin
      rst_b=0;
      #5;
      rst_b=1;
    end
    
    initial begin
      c_up=1;
      #60;
      c_up=0;
      #10;
      c_up=1;
    end
    
    initial begin
      clr=0;
      #40;
      clr=1;
      #10;
      clr=0;
    end
    
    
    
    
    
  endmodule

lab5/simulation.vcd
$date
	Mon Dec 02 14:59:12 2024
$end
$version
	ModelSim Version 6.5b
$end
$timescale
	1ps
$end
$scope module counter_tb $end
$var parameter 32 ! size $end
$var parameter 8 " init $end
$var reg 1 # clk $end
$var reg 1 $ rst_b $end
$var reg 1 % c_up $end
$var reg 1 & clr $end
$var wire 1 ' q [7] $end
$var wire 1 ( q [6] $end
$var wire 1 ) q [5] $end
$var wire 1 * q [4] $end
$var wire 1 + q [3] $end
$var wire 1 , q [2] $end
$var wire 1 - q [1] $end
$var wire 1 . q [0] $end
$scope module dut $end
$var parameter 32 / size $end
$var parameter 8 0 init $end
$var wire 1 1 clk $end
$var wire 1 2 rst_b $end
$var wire 1 3 c_up $end
$var wire 1 4 clr $end
$var reg 8 5 q [7:0] $end
$upscope $end
$upscope $end
$enddefinitions $end
#0
$dumpvars
b1000 !
b11111111 "
b1000 /
b11111111 0
0#
0$
1%
0&
b11111111 5
1.
1-
1,
1+
1*
1)
1(
1'
04
13
02
01
$end
#5
1#
1$
11
12
b0 5
0.
0-
0,
0+
0*
0)
0(
0'
#10
0#
01
#15
1#
11
b1 5
1.
#20
0#
01
#25
1#
11
b10 5
0.
1-
#30
0#
01
#35
1#
11
b11 5
1.
#40
1&
0#
14
01
#45
0&
1#
04
11
b100 5
0.
0-
1,
#50
0%
0#
03
01
#55
1%
1#
13
11
b101 5
1.
#60
0#
01
#65
1#
11
b110 5
0.
1-
#70
0#
01
#75
1#
11
b111 5
1.
#80
0#
01
#85
1#
11
b1000 5
0.
0-
0,
1+
#90
0#
01
#95
1#
11
b1001 5
1.
#100
0#
01
#105
1#
11
b1010 5
0.
1-
#110
0#
01
#115
1#
11
b1011 5
1.
#120
0#
01
#125
1#
11
b1100 5
0.
0-
1,
#130
0#
01
#135
1#
11
b1101 5
1.
#140
0#
01
#145
1#
11
b1110 5
0.
1-
#150
0#
01
#155
1#
11
b1111 5
1.
#160
0#
01
#165
1#
11
b10000 5
0.
0-
0,
0+
1*
#170
0#
01
#175
1#
11
b10001 5
1.
#180
0#
01
#185
1#
11
b10010 5
0.
1-
#190
0#
01
#195
1#
11
b10011 5
1.
#200
0#
01
#205
1#
11
b10100 5
0.
0-
1,
#210
0#
01
#215
1#
11
b10101 5
1.
#220
0#
01
#225
1#
11
b10110 5
0.
1-
#230
0#
01
#235
1#
11
b10111 5
1.
#240
0#
01
#245
1#
11
b11000 5
0.
0-
0,
1+
#250
0#
01
#255
1#
11
b11001 5
1.
#260
0#
01
#265
1#
11
b11010 5
0.
1-
#270
0#
01
#275
1#
11
b11011 5
1.
#280
0#
01
#285
1#
11
b11100 5
0.
0-
1,
#290
0#
01
#295
1#
11
b11101 5
1.
#300
0#
01
#305
1#
11
b11110 5
0.
1-
#310
0#
01
#315
1#
11
b11111 5
1.
#320
0#
01
#325
1#
11
b100000 5
0.
0-
0,
0+
0*
1)
#330
0#
01
#335
1#
11
b100001 5
1.
#340
0#
01
#345
1#
11
b100010 5
0.
1-
#350
0#
01
#355
1#
11
b100011 5
1.
#360
0#
01
#365
1#
11
b100100 5
0.
0-
1,
#370
0#
01
#375
1#
11
b100101 5
1.
#380
0#
01
#385
1#
11
b100110 5
0.
1-
#390
0#
01
#395
1#
11
b100111 5
1.
#400
0#
01
#405
1#
11
b101000 5
0.
0-
0,
1+
#410
0#
01
#415
1#
11
b101001 5
1.
#420
0#
01
#425
1#
11
b101010 5
0.
1-
#430
0#
01
#435
1#
11
b101011 5
1.
#440
0#
01
#445
1#
11
b101100 5
0.
0-
1,
#450
0#
01
#455
1#
11
b101101 5
1.
#460
0#
01
#465
1#
11
b101110 5
0.
1-
#470
0#
01
#475
1#
11
b101111 5
1.
#480
0#
01
#485
1#
11
b110000 5
0.
0-
0,
0+
1*
#490
0#
01
#495
1#
11
b110001 5
1.
